payir/__init__.py
payir/admin.py
payir/apps.py
payir/exceptions.py
payir/models.py
payir/locale/fa_IR/LC_MESSAGES/django.mo
django_payir-0.1.2.dist-info/METADATA
django_payir-0.1.2.dist-info/WHEEL
django_payir-0.1.2.dist-info/top_level.txt
django_payir-0.1.2.dist-info/RECORD
