Metadata-Version: 2.1
Name: django-payir
Version: 0.1.2
Summary: A pluggable Django application for integrating Pay.ir into your website.
Home-page: https://github.com/farahmand-m/django-payir
Author: Mohammad Farahmand
License: MIT
Keywords: payment,gateway,pay.ir
Platform: any
Requires-Python: ~=3.7
Requires-Dist: django (~=2.2.11)
Requires-Dist: requests (==2.23.0)
